hatch_cada/__init__.py
hatch_cada/constants.py
hatch_cada/hook.py
hatch_cada/lockfile.py
hatch_cada/py.typed
hatch_cada/pyproject.py
hatch_cada/strategy.py
hatch_cada/utils.py
hatch_cada-1.0.0.dist-info/METADATA
hatch_cada-1.0.0.dist-info/WHEEL
hatch_cada-1.0.0.dist-info/entry_points.txt
hatch_cada-1.0.0.dist-info/licenses/LICENSE
hatch_cada-1.0.0.dist-info/RECORD
