Metadata-Version: 2.4
Name: hatch-cada
Version: 1.0.0
Summary: Hatchling metadata hook that rewrites workspace dependencies with version constraints at build time
Project-URL: Homepage, https://github.com/bilelomrani1/hatch-cada
Project-URL: Repository, https://github.com/bilelomrani1/hatch-cada
Project-URL: Issues, https://github.com/bilelomrani1/hatch-cada/issues
Project-URL: Changelog, https://github.com/bilelomrani1/hatch-cada/blob/main/CHANGELOG.md
Author-email: Bilel Omrani <bilelomrani1@gmail.com>
Maintainer-email: Bilel Omrani <bilelomrani1@gmail.com>
License-File: LICENSE
Keywords: build,dependency,hatch,packaging,plugin,publishing,release,versioning
Classifier: Development Status :: 3 - Alpha
Classifier: Intended Audience :: Developers
Classifier: Operating System :: OS Independent
Classifier: Programming Language :: Python
Classifier: Programming Language :: Python :: 3
Classifier: Programming Language :: Python :: 3 :: Only
Classifier: Programming Language :: Python :: 3.10
Classifier: Programming Language :: Python :: 3.11
Classifier: Programming Language :: Python :: 3.12
Classifier: Programming Language :: Python :: 3.13
Classifier: Programming Language :: Python :: 3.14
Classifier: Topic :: Software Development :: Build Tools
Classifier: Typing :: Typed
Requires-Python: >=3.10
Requires-Dist: hatchling>=1.28.0
Requires-Dist: packaging>=25.0
Requires-Dist: tomli; python_version < '3.11'
